{"metadata": {"dbt_schema_version": "https://schemas.getdbt.com/dbt/run-results/v6.json", "dbt_version": "1.9.1", "generated_at": "2025-01-22T05:44:36.578562Z", "invocation_id": "44287141-4d0a-4e3d-b626-090da2fded00", "env": {}}, "results": [{"status": "success", "timing": [{"name": "compile", "started_at": "2025-01-22T05:44:36.438174Z", "completed_at": "2025-01-22T05:44:36.447389Z"}, {"name": "execute", "started_at": "2025-01-22T05:44:36.448103Z", "completed_at": "2025-01-22T05:44:36.448123Z"}], "thread_id": "Thread-1 (worker)", "execution_time": 0.011374235153198242, "adapter_response": {}, "message": null, "failures": null, "unique_id": "model.dbt_project.my_first_dbt_model", "compiled": true, "compiled_code": "/*\n    Welcome to your first dbt model!\n    Did you know that you can also configure models directly within SQL files?\n    This will override configurations stated in dbt_project.yml\n\n    Try changing \"table\" to \"view\" below\n*/\n\n\n\nwith source_data as (\n\n    select 1 as id\n    union all\n    select null as id\n\n)\n\nselect *\nfrom source_data\n\n/*\n    Uncomment the line below to remove records with null `id` values\n*/\n\n-- where id is not null", "relation_name": "\"dev\".\"main\".\"my_first_dbt_model\"", "batch_results": null}, {"status": "success", "timing": [{"name": "compile", "started_at": "2025-01-22T05:44:36.451427Z", "completed_at": "2025-01-22T05:44:36.453432Z"}, {"name": "execute", "started_at": "2025-01-22T05:44:36.454054Z", "completed_at": "2025-01-22T05:44:36.454065Z"}], "thread_id": "Thread-1 (worker)", "execution_time": 0.004293680191040039, "adapter_response": {}, "message": null, "failures": null, "unique_id": "seed.dbt_project.Dodge", "compiled": null, "compiled_code": null, "relation_name": null, "batch_results": null}, {"status": "success", "timing": [{"name": "compile", "started_at": "2025-01-22T05:44:36.456898Z", "completed_at": "2025-01-22T05:44:36.458713Z"}, {"name": "execute", "started_at": "2025-01-22T05:44:36.459332Z", "completed_at": "2025-01-22T05:44:36.459344Z"}], "thread_id": "Thread-1 (worker)", "execution_time": 0.0038709640502929688, "adapter_response": {}, "message": null, "failures": null, "unique_id": "seed.dbt_project.Dodge_2020_and_newer", "compiled": null, "compiled_code": null, "relation_name": null, "batch_results": null}, {"status": "success", "timing": [{"name": "compile", "started_at": "2025-01-22T05:44:36.462157Z", "completed_at": "2025-01-22T05:44:36.463887Z"}, {"name": "execute", "started_at": "2025-01-22T05:44:36.464456Z", "completed_at": "2025-01-22T05:44:36.464468Z"}], "thread_id": "Thread-1 (worker)", "execution_time": 0.0036160945892333984, "adapter_response": {}, "message": null, "failures": null, "unique_id": "seed.dbt_project.Ford", "compiled": null, "compiled_code": null, "relation_name": null, "batch_results": null}, {"status": "success", "timing": [{"name": "compile", "started_at": "2025-01-22T05:44:36.467289Z", "completed_at": "2025-01-22T05:44:36.468976Z"}, {"name": "execute", "started_at": "2025-01-22T05:44:36.469566Z", "completed_at": "2025-01-22T05:44:36.469574Z"}], "thread_id": "Thread-1 (worker)", "execution_time": 0.0035779476165771484, "adapter_response": {}, "message": null, "failures": null, "unique_id": "seed.dbt_project.Ford_2020_and_newer", "compiled": null, "compiled_code": null, "relation_name": null, "batch_results": null}, {"status": "success", "timing": [{"name": "compile", "started_at": "2025-01-22T05:44:36.472289Z", "completed_at": "2025-01-22T05:44:36.473781Z"}, {"name": "execute", "started_at": "2025-01-22T05:44:36.474361Z", "completed_at": "2025-01-22T05:44:36.474369Z"}], "thread_id": "Thread-1 (worker)", "execution_time": 0.0033388137817382812, "adapter_response": {}, "message": null, "failures": null, "unique_id": "seed.dbt_project.Hyundai", "compiled": null, "compiled_code": null, "relation_name": null, "batch_results": null}, {"status": "success", "timing": [{"name": "compile", "started_at": "2025-01-22T05:44:36.478049Z", "completed_at": "2025-01-22T05:44:36.481102Z"}, {"name": "execute", "started_at": "2025-01-22T05:44:36.481708Z", "completed_at": "2025-01-22T05:44:36.481719Z"}], "thread_id": "Thread-1 (worker)", "execution_time": 0.005585193634033203, "adapter_response": {}, "message": null, "failures": null, "unique_id": "seed.dbt_project.Hyundai_2020_and_newer", "compiled": null, "compiled_code": null, "relation_name": null, "batch_results": null}, {"status": "success", "timing": [{"name": "compile", "started_at": "2025-01-22T05:44:36.484637Z", "completed_at": "2025-01-22T05:44:36.486294Z"}, {"name": "execute", "started_at": "2025-01-22T05:44:36.486876Z", "completed_at": "2025-01-22T05:44:36.486889Z"}], "thread_id": "Thread-1 (worker)", "execution_time": 0.003694772720336914, "adapter_response": {}, "message": null, "failures": null, "unique_id": "seed.dbt_project.Jeep", "compiled": null, "compiled_code": null, "relation_name": null, "batch_results": null}, {"status": "success", "timing": [{"name": "compile", "started_at": "2025-01-22T05:44:36.489632Z", "completed_at": "2025-01-22T05:44:36.491165Z"}, {"name": "execute", "started_at": "2025-01-22T05:44:36.491714Z", "completed_at": "2025-01-22T05:44:36.491721Z"}], "thread_id": "Thread-1 (worker)", "execution_time": 0.003340005874633789, "adapter_response": {}, "message": null, "failures": null, "unique_id": "seed.dbt_project.Jeep_2020_and_newer", "compiled": null, "compiled_code": null, "relation_name": null, "batch_results": null}, {"status": "success", "timing": [{"name": "compile", "started_at": "2025-01-22T05:44:36.494399Z", "completed_at": "2025-01-22T05:44:36.495951Z"}, {"name": "execute", "started_at": "2025-01-22T05:44:36.496510Z", "completed_at": "2025-01-22T05:44:36.496517Z"}], "thread_id": "Thread-1 (worker)", "execution_time": 0.003350973129272461, "adapter_response": {}, "message": null, "failures": null, "unique_id": "seed.dbt_project.Kaggle_2024_vehicles", "compiled": null, "compiled_code": null, "relation_name": null, "batch_results": null}, {"status": "success", "timing": [{"name": "compile", "started_at": "2025-01-22T05:44:36.499209Z", "completed_at": "2025-01-22T05:44:36.500759Z"}, {"name": "execute", "started_at": "2025-01-22T05:44:36.501333Z", "completed_at": "2025-01-22T05:44:36.501340Z"}], "thread_id": "Thread-1 (worker)", "execution_time": 0.0033936500549316406, "adapter_response": {}, "message": null, "failures": null, "unique_id": "seed.dbt_project.Ram", "compiled": null, "compiled_code": null, "relation_name": null, "batch_results": null}, {"status": "success", "timing": [{"name": "compile", "started_at": "2025-01-22T05:44:36.504133Z", "completed_at": "2025-01-22T05:44:36.505625Z"}, {"name": "execute", "started_at": "2025-01-22T05:44:36.506262Z", "completed_at": "2025-01-22T05:44:36.506269Z"}], "thread_id": "Thread-1 (worker)", "execution_time": 0.003600597381591797, "adapter_response": {}, "message": null, "failures": null, "unique_id": "seed.dbt_project.Ram_2020_and_newer", "compiled": null, "compiled_code": null, "relation_name": null, "batch_results": null}, {"status": "success", "timing": [{"name": "compile", "started_at": "2025-01-22T05:44:36.509299Z", "completed_at": "2025-01-22T05:44:36.510729Z"}, {"name": "execute", "started_at": "2025-01-22T05:44:36.511324Z", "completed_at": "2025-01-22T05:44:36.511331Z"}], "thread_id": "Thread-1 (worker)", "execution_time": 0.003678560256958008, "adapter_response": {}, "message": null, "failures": null, "unique_id": "seed.dbt_project.all_vehicles_model", "compiled": null, "compiled_code": null, "relation_name": null, "batch_results": null}, {"status": "success", "timing": [{"name": "compile", "started_at": "2025-01-22T05:44:36.514256Z", "completed_at": "2025-01-22T05:44:36.517822Z"}, {"name": "execute", "started_at": "2025-01-22T05:44:36.518472Z", "completed_at": "2025-01-22T05:44:36.518480Z"}], "thread_id": "Thread-1 (worker)", "execution_time": 0.005550384521484375, "adapter_response": {}, "message": null, "failures": null, "unique_id": "model.dbt_project.my_second_dbt_model", "compiled": true, "compiled_code": "-- Use the `ref` function to select from other models\n\nselect *\nfrom \"dev\".\"main\".\"my_first_dbt_model\"\nwhere id = 1", "relation_name": "\"dev\".\"main\".\"my_second_dbt_model\"", "batch_results": null}, {"status": "success", "timing": [{"name": "compile", "started_at": "2025-01-22T05:44:36.521478Z", "completed_at": "2025-01-22T05:44:36.537784Z"}, {"name": "execute", "started_at": "2025-01-22T05:44:36.538459Z", "completed_at": "2025-01-22T05:44:36.538470Z"}], "thread_id": "Thread-1 (worker)", "execution_time": 0.01834845542907715, "adapter_response": {}, "message": null, "failures": null, "unique_id": "test.dbt_project.not_null_my_first_dbt_model_id.5fb22c2710", "compiled": true, "compiled_code": "\n    \n    \n\n\n\nselect id\nfrom \"dev\".\"main\".\"my_first_dbt_model\"\nwhere id is null\n\n\n", "relation_name": null, "batch_results": null}, {"status": "success", "timing": [{"name": "compile", "started_at": "2025-01-22T05:44:36.541413Z", "completed_at": "2025-01-22T05:44:36.549231Z"}, {"name": "execute", "started_at": "2025-01-22T05:44:36.549826Z", "completed_at": "2025-01-22T05:44:36.549835Z"}], "thread_id": "Thread-1 (worker)", "execution_time": 0.009795427322387695, "adapter_response": {}, "message": null, "failures": null, "unique_id": "test.dbt_project.unique_my_first_dbt_model_id.16e066b321", "compiled": true, "compiled_code": "\n    \n    \n\nselect\n    id as unique_field,\n    count(*) as n_records\n\nfrom \"dev\".\"main\".\"my_first_dbt_model\"\nwhere id is not null\ngroup by id\nhaving count(*) > 1\n\n\n", "relation_name": null, "batch_results": null}, {"status": "success", "timing": [{"name": "compile", "started_at": "2025-01-22T05:44:36.552784Z", "completed_at": "2025-01-22T05:44:36.556136Z"}, {"name": "execute", "started_at": "2025-01-22T05:44:36.556727Z", "completed_at": "2025-01-22T05:44:36.556737Z"}], "thread_id": "Thread-1 (worker)", "execution_time": 0.0054509639739990234, "adapter_response": {}, "message": null, "failures": null, "unique_id": "model.dbt_project.explore_all_vehicles_model", "compiled": true, "compiled_code": "select *\nfrom \"dev\".\"main\".\"all_vehicles_model\"", "relation_name": "\"dev\".\"main\".\"explore_all_vehicles_model\"", "batch_results": null}, {"status": "success", "timing": [{"name": "compile", "started_at": "2025-01-22T05:44:36.559524Z", "completed_at": "2025-01-22T05:44:36.564516Z"}, {"name": "execute", "started_at": "2025-01-22T05:44:36.565156Z", "completed_at": "2025-01-22T05:44:36.565165Z"}], "thread_id": "Thread-1 (worker)", "execution_time": 0.006926774978637695, "adapter_response": {}, "message": null, "failures": null, "unique_id": "test.dbt_project.not_null_my_second_dbt_model_id.151b76d778", "compiled": true, "compiled_code": "\n    \n    \n\n\n\nselect id\nfrom \"dev\".\"main\".\"my_second_dbt_model\"\nwhere id is null\n\n\n", "relation_name": null, "batch_results": null}, {"status": "success", "timing": [{"name": "compile", "started_at": "2025-01-22T05:44:36.568172Z", "completed_at": "2025-01-22T05:44:36.574958Z"}, {"name": "execute", "started_at": "2025-01-22T05:44:36.575571Z", "completed_at": "2025-01-22T05:44:36.575582Z"}], "thread_id": "Thread-1 (worker)", "execution_time": 0.008963346481323242, "adapter_response": {}, "message": null, "failures": null, "unique_id": "test.dbt_project.unique_my_second_dbt_model_id.57a0f8c493", "compiled": true, "compiled_code": "\n    \n    \n\nselect\n    id as unique_field,\n    count(*) as n_records\n\nfrom \"dev\".\"main\".\"my_second_dbt_model\"\nwhere id is not null\ngroup by id\nhaving count(*) > 1\n\n\n", "relation_name": null, "batch_results": null}], "elapsed_time": 0.2859179973602295, "args": {"profiles_dir": "/root/.dbt", "show_resource_report": false, "static_parser": true, "strict_mode": false, "which": "generate", "invocation_command": "dbt docs generate", "log_path": "/content/car-data-project/dbt_project/logs", "use_colors": true, "empty_catalog": false, "require_resource_names_without_spaces": false, "vars": {}, "log_level_file": "debug", "partial_parse_file_diff": true, "project_dir": "/content/car-data-project/dbt_project", "log_format_file": "debug", "populate_cache": true, "write_json": true, "source_freshness_run_project_hooks": false, "require_nested_cumulative_type_params": false, "print": true, "quiet": false, "introspect": true, "exclude": [], "warn_error_options": {"include": [], "exclude": []}, "compile": true, "state_modified_compare_vars": false, "printer_width": 80, "skip_nodes_if_on_run_start_fails": false, "use_colors_file": true, "require_yaml_configuration_for_mf_time_spines": false, "indirect_selection": "eager", "send_anonymous_usage_stats": true, "defer": false, "macro_debugging": false, "partial_parse": true, "log_format": "default", "require_explicit_package_overrides_for_builtin_materializations": true, "state_modified_compare_more_unrendered_values": false, "require_batched_execution_for_custom_microbatch_strategy": false, "select": [], "static": false, "log_level": "info", "cache_selected_only": false, "log_file_max_bytes": 10485760, "version_check": true, "favor_state": false}}